[
   {
       "command":"Ping",
       "type":"contains",
       "answer":"Anjing" 
   },
   {
       "command":"Ping",
       "type":"contains",
       "answer":"Anjing" 
   },
   {
       "command":"Ping",
       "type":"contains",
       "answer":"Anjing" 
   },
   {
       "command":"Ping",
       "type":"contains",
       "answer":"Anjing" 
   },
   {
       "command":"Ping",
       "type":"contains",
       "answer":"Anjing" 
   },
   {
       "command":"Ping
P",
       "type":"contains",
       "answer":"Anjing memek kntl" 
   }
]